README.txt
setup.cfg
setup.py
docs/HISTORY.txt
docs/INSTALL.txt
docs/LICENSE.GPL
docs/LICENSE.txt
easyshop/__init__.py
easyshop.taxes.egg-info/PKG-INFO
easyshop.taxes.egg-info/SOURCES.txt
easyshop.taxes.egg-info/dependency_links.txt
easyshop.taxes.egg-info/entry_points.txt
easyshop.taxes.egg-info/namespace_packages.txt
easyshop.taxes.egg-info/not-zip-safe
easyshop.taxes.egg-info/requires.txt
easyshop.taxes.egg-info/top_level.txt
easyshop/taxes/__init__.py
easyshop/taxes/configure.zcml
easyshop/taxes/profiles.zcml
easyshop/taxes/tests.py
easyshop/taxes/adapters/__init__.py
easyshop/taxes/adapters/configure.zcml
easyshop/taxes/adapters/tax_management.py
easyshop/taxes/browser/__init__.py
easyshop/taxes/browser/configure.zcml
easyshop/taxes/browser/tax.pt
easyshop/taxes/browser/tax.py
easyshop/taxes/browser/taxes_view.pt
easyshop/taxes/browser/taxes_view.py
easyshop/taxes/content/__init__.py
easyshop/taxes/content/customer_tax.py
easyshop/taxes/content/default_tax.py
easyshop/taxes/content/taxes_container.py
easyshop/taxes/profiles/default/factorytool.xml
easyshop/taxes/profiles/default/types.xml
easyshop/taxes/profiles/default/workflows.xml
easyshop/taxes/profiles/default/types/CustomerTax.xml
easyshop/taxes/profiles/default/types/DefaultTax.xml
easyshop/taxes/profiles/default/types/TaxesContainer.xml